b_class_worth_calculator/__init__.py
b_class_worth_calculator/main.py
b_class_worth_calculator-1.0.2.dist-info/licenses/LICENSE
b_class_worth_calculator-1.0.2.dist-info/METADATA
b_class_worth_calculator-1.0.2.dist-info/WHEEL
b_class_worth_calculator-1.0.2.dist-info/entry_points.txt
b_class_worth_calculator-1.0.2.dist-info/top_level.txt
b_class_worth_calculator-1.0.2.dist-info/RECORD
