Metadata-Version: 2.4
Name: b-class-worth-calculator
Version: 1.0.2
Summary: 智能工作性价比分析工具，综合评估薪资、工时、通勤等多维度因素，支持生成可视化报告
Home-page: https://github.com/trae-ai/b-class-worth-calculator
Author: TraeAI
Author-email: support@trae.ai
Project-URL: Bug Reports, https://github.com/trae-ai/b-class-worth-calculator/issues
Project-URL: Source, https://github.com/trae-ai/b-class-worth-calculator
Project-URL: Documentation, https://github.com/trae-ai/b-class-worth-calculator/blob/main/README.md
Keywords: job,salary,calculator,work,worth,analysis,career,mcp,tool,productivity,visualization,工作,薪资,计算器,性价比,分析,职业
Classifier: Development Status :: 5 - Production/Stable
Classifier: Intended Audience :: Developers
Classifier: Intended Audience :: End Users/Desktop
Classifier: License :: OSI Approved :: MIT License
Classifier: Operating System :: OS Independent
Classifier: Programming Language :: Python :: 3
Classifier: Programming Language :: Python :: 3.8
Classifier: Programming Language :: Python :: 3.9
Classifier: Programming Language :: Python :: 3.10
Classifier: Programming Language :: Python :: 3.11
Classifier: Programming Language :: Python :: 3.12
Classifier: Topic :: Office/Business
Classifier: Topic :: Scientific/Engineering :: Information Analysis
Classifier: Topic :: Utilities
Requires-Python: >=3.8
License-File: LICENSE
Requires-Dist: mcp>=1.0.0
Requires-Dist: fastmcp>=0.1.0
Requires-Dist: playwright>=1.40.0
Requires-Dist: jinja2>=3.1.0
Requires-Dist: pillow>=10.0.0
Dynamic: author
Dynamic: author-email
Dynamic: classifier
Dynamic: description
Dynamic: description-content-type
Dynamic: home-page
Dynamic: keywords
Dynamic: license-file
Dynamic: project-url
Dynamic: requires-dist
Dynamic: requires-python
Dynamic: summary
